{"is_source_file": true, "format": "JavaScript", "description": "This file defines an API client class for interacting with backend services, providing methods for CRUD operations on models, roles, mappings, and other entities, as well as handling configuration for mock or real backend requests.", "external_files": ["fetch API (builtin)"], "external_methods": ["fetch"], "published": ["createApiClient", "ApiClient"], "classes": [{"name": "ApiClient", "description": "A class that manages HTTP requests to backend APIs, encapsulating logic for authorization headers, request building, and specific API endpoints."}], "methods": [{"name": "constructor({ bypassAuth, baseUrl, getAccessToken })", "description": "Initializes the ApiClient with options for bypassing auth, base URL, and access token retrieval.", "scope": "ApiClient", "scopeKind": "class"}, {"name": "_headers()", "description": "Builds and returns the HTTP headers, including Authorization if access token is available.", "scope": "ApiClient", "scopeKind": "class"}, {"name": "listModels()", "description": "Fetches a list of models from the backend.", "scope": "ApiClient", "scopeKind": "class"}, {"name": "createModel(data)", "description": "Creates a new model with the provided data.", "scope": "ApiClient", "scopeKind": "class"}, {"name": "getModel(id)", "description": "Retrieves a specific model by its ID.", "scope": "ApiClient", "scopeKind": "class"}, {"name": "updateModel(id, data)", "description": "Updates an existing model identified by its ID.", "scope": "ApiClient", "scopeKind": "class"}, {"name": "deleteModel(id)", "description": "Deletes a model by its ID.", "scope": "ApiClient", "scopeKind": "class"}, {"name": "listRoles()", "description": "Fetches a list of roles.", "scope": "ApiClient", "scopeKind": "class"}, {"name": "createRole(data)", "description": "Creates a new role with the provided data.", "scope": "ApiClient", "scopeKind": "class"}, {"name": "listMappings()", "description": "Fetches a list of mappings.", "scope": "ApiClient", "scopeKind": "class"}, {"name": "createMapping(data)", "description": "Creates a new mapping with the provided data.", "scope": "ApiClient", "scopeKind": "class"}, {"name": "validate(payload)", "description": "Validates a given payload.", "scope": "ApiClient", "scopeKind": "class"}, {"name": "getCollaboration()", "description": "Retrieves collaboration data.", "scope": "ApiClient", "scopeKind": "class"}, {"name": "updateCollaboration(payload)", "description": "Updates collaboration data with the provided payload.", "scope": "ApiClient", "scopeKind": "class"}, {"name": "importModel(payload)", "description": "Imports a model with the provided payload.", "scope": "ApiClient", "scopeKind": "class"}, {"name": "exportModel(id)", "description": "Exports a model by its ID.", "scope": "ApiClient", "scopeKind": "class"}, {"name": "deviceConnection(payload)", "description": "Handles device connection with provided payload.", "scope": "ApiClient", "scopeKind": "class"}, {"name": "log(payload)", "description": "Sends log data to the server.", "scope": "ApiClient", "scopeKind": "class"}, {"name": "_request(path, options)", "description": "Internal method to perform fetch requests with proper headers and error handling.", "scope": "ApiClient", "scopeKind": "class"}, {"name": "createApiClient(getAccessToken)", "scope": "", "scopeKind": "", "description": "unavailable"}], "calls": ["this._request", "fetch"], "search-terms": ["ApiClient", "fetch", "API request methods", "model management", "mock backend", "authorization headers"], "state": 2, "file_id": 13, "knowledge_revision": 27, "git_revision": "", "ctags": [{"_type": "tag", "name": "ApiClient", "path": "/home/kavia/workspace/code-generation/modelmapperv1-1604-2665/DesignStudioFrontend/src/services/apiClient.js", "pattern": "/^export class ApiClient {$/", "language": "JavaScript", "kind": "class"}, {"_type": "tag", "name": "Content-Type", "path": "/home/kavia/workspace/code-generation/modelmapperv1-1604-2665/DesignStudioFrontend/src/services/apiClient.js", "pattern": "/^    const headers = { 'Content-Type': 'application\\/json' };$/", "language": "JavaScript", "kind": "property", "scope": "ApiClient._headers.headers", "scopeKind": "class"}, {"_type": "tag", "name": "_headers", "path": "/home/kavia/workspace/code-generation/modelmapperv1-1604-2665/DesignStudioFrontend/src/services/apiClient.js", "pattern": "/^  _headers() {$/", "language": "JavaScript", "kind": "method", "signature": "()", "scope": "ApiClient", "scopeKind": "class"}, {"_type": "tag", "name": "_request", "path": "/home/kavia/workspace/code-generation/modelmapperv1-1604-2665/DesignStudioFrontend/src/services/apiClient.js", "pattern": "/^  async _request(path, options) {$/", "language": "JavaScript", "kind": "method", "signature": "(path, options)", "scope": "ApiClient", "scopeKind": "class"}, {"_type": "tag", "name": "constructor", "path": "/home/kavia/workspace/code-generation/modelmapperv1-1604-2665/DesignStudioFrontend/src/services/apiClient.js", "pattern": "/^  constructor({ bypassAuth, baseUrl, getAccessToken }) {$/", "language": "JavaScript", "kind": "method", "signature": "({ bypassAuth, baseUrl, getAccessToken })", "scope": "ApiClient", "scopeKind": "class"}, {"_type": "tag", "name": "createApiClient", "path": "/home/kavia/workspace/code-generation/modelmapperv1-1604-2665/DesignStudioFrontend/src/services/apiClient.js", "pattern": "/^export function createApiClient(getAccessToken) {$/", "language": "JavaScript", "kind": "function", "signature": "(getAccessToken)"}, {"_type": "tag", "name": "createMapping", "path": "/home/kavia/workspace/code-generation/modelmapperv1-1604-2665/DesignStudioFrontend/src/services/apiClient.js", "pattern": "/^  async createMapping(data) {$/", "language": "JavaScript", "kind": "method", "signature": "(data)", "scope": "ApiClient", "scopeKind": "class"}, {"_type": "tag", "name": "createModel", "path": "/home/kavia/workspace/code-generation/modelmapperv1-1604-2665/DesignStudioFrontend/src/services/apiClient.js", "pattern": "/^  async createModel(data) {$/", "language": "JavaScript", "kind": "method", "signature": "(data)", "scope": "ApiClient", "scopeKind": "class"}, {"_type": "tag", "name": "createRole", "path": "/home/kavia/workspace/code-generation/modelmapperv1-1604-2665/DesignStudioFrontend/src/services/apiClient.js", "pattern": "/^  async createRole(data) {$/", "language": "JavaScript", "kind": "method", "signature": "(data)", "scope": "ApiClient", "scopeKind": "class"}, {"_type": "tag", "name": "deleteModel", "path": "/home/kavia/workspace/code-generation/modelmapperv1-1604-2665/DesignStudioFrontend/src/services/apiClient.js", "pattern": "/^  async deleteModel(id) {$/", "language": "JavaScript", "kind": "method", "signature": "(id)", "scope": "ApiClient", "scopeKind": "class"}, {"_type": "tag", "name": "deviceConnection", "path": "/home/kavia/workspace/code-generation/modelmapperv1-1604-2665/DesignStudioFrontend/src/services/apiClient.js", "pattern": "/^  async deviceConnection(payload) {$/", "language": "JavaScript", "kind": "method", "signature": "(payload)", "scope": "ApiClient", "scopeKind": "class"}, {"_type": "tag", "name": "exportModel", "path": "/home/kavia/workspace/code-generation/modelmapperv1-1604-2665/DesignStudioFrontend/src/services/apiClient.js", "pattern": "/^  async exportModel(id) {$/", "language": "JavaScript", "kind": "method", "signature": "(id)", "scope": "ApiClient", "scopeKind": "class"}, {"_type": "tag", "name": "getCollaboration", "path": "/home/kavia/workspace/code-generation/modelmapperv1-1604-2665/DesignStudioFrontend/src/services/apiClient.js", "pattern": "/^  async getCollaboration() {$/", "language": "JavaScript", "kind": "method", "signature": "()", "scope": "ApiClient", "scopeKind": "class"}, {"_type": "tag", "name": "getModel", "path": "/home/kavia/workspace/code-generation/modelmapperv1-1604-2665/DesignStudioFrontend/src/services/apiClient.js", "pattern": "/^  async getModel(id) {$/", "language": "JavaScript", "kind": "method", "signature": "(id)", "scope": "ApiClient", "scopeKind": "class"}, {"_type": "tag", "name": "headers", "path": "/home/kavia/workspace/code-generation/modelmapperv1-1604-2665/DesignStudioFrontend/src/services/apiClient.js", "pattern": "/^    const headers = { 'Content-Type': 'application\\/json' };$/", "language": "JavaScript", "kind": "class", "scope": "ApiClient._headers", "scopeKind": "class"}, {"_type": "tag", "name": "importModel", "path": "/home/kavia/workspace/code-generation/modelmapperv1-1604-2665/DesignStudioFrontend/src/services/apiClient.js", "pattern": "/^  async importModel(payload) {$/", "language": "JavaScript", "kind": "method", "signature": "(payload)", "scope": "ApiClient", "scopeKind": "class"}, {"_type": "tag", "name": "listMappings", "path": "/home/kavia/workspace/code-generation/modelmapperv1-1604-2665/DesignStudioFrontend/src/services/apiClient.js", "pattern": "/^  async listMappings() {$/", "language": "JavaScript", "kind": "method", "signature": "()", "scope": "ApiClient", "scopeKind": "class"}, {"_type": "tag", "name": "listModels", "path": "/home/kavia/workspace/code-generation/modelmapperv1-1604-2665/DesignStudioFrontend/src/services/apiClient.js", "pattern": "/^  async listModels() {$/", "language": "JavaScript", "kind": "method", "signature": "()", "scope": "ApiClient", "scopeKind": "class"}, {"_type": "tag", "name": "listRoles", "path": "/home/kavia/workspace/code-generation/modelmapperv1-1604-2665/DesignStudioFrontend/src/services/apiClient.js", "pattern": "/^  async listRoles() {$/", "language": "JavaScript", "kind": "method", "signature": "()", "scope": "ApiClient", "scopeKind": "class"}, {"_type": "tag", "name": "log", "path": "/home/kavia/workspace/code-generation/modelmapperv1-1604-2665/DesignStudioFrontend/src/services/apiClient.js", "pattern": "/^  async log(payload) {$/", "language": "JavaScript", "kind": "method", "signature": "(payload)", "scope": "ApiClient", "scopeKind": "class"}, {"_type": "tag", "name": "updateCollaboration", "path": "/home/kavia/workspace/code-generation/modelmapperv1-1604-2665/DesignStudioFrontend/src/services/apiClient.js", "pattern": "/^  async updateCollaboration(payload) {$/", "language": "JavaScript", "kind": "method", "signature": "(payload)", "scope": "ApiClient", "scopeKind": "class"}, {"_type": "tag", "name": "updateModel", "path": "/home/kavia/workspace/code-generation/modelmapperv1-1604-2665/DesignStudioFrontend/src/services/apiClient.js", "pattern": "/^  async updateModel(id, data) {$/", "language": "JavaScript", "kind": "method", "signature": "(id, data)", "scope": "ApiClient", "scopeKind": "class"}, {"_type": "tag", "name": "validate", "path": "/home/kavia/workspace/code-generation/modelmapperv1-1604-2665/DesignStudioFrontend/src/services/apiClient.js", "pattern": "/^  async validate(payload) {$/", "language": "JavaScript", "kind": "method", "signature": "(payload)", "scope": "ApiClient", "scopeKind": "class"}], "hash": "3fa06ddbed3d3a7dedb04450c48ef3f2", "format-version": 4, "code-base-name": "DesignStudioFrontend", "filename": "DesignStudioFrontend/src/services/apiClient.js", "fields": [{"name": "const headers = { 'Content-Type': 'application\\/json' };", "scope": "ApiClient._headers.headers", "scopeKind": "class", "description": "unavailable"}], "revision_history": [{"27": ""}]}